generate_pyproject/__init__.py
generate_pyproject/generate_pyproject.py
ops_py_generate_pyproject-2.2.3.dist-info/LICENSE
ops_py_generate_pyproject-2.2.3.dist-info/METADATA
ops_py_generate_pyproject-2.2.3.dist-info/WHEEL
ops_py_generate_pyproject-2.2.3.dist-info/top_level.txt
ops_py_generate_pyproject-2.2.3.dist-info/RECORD
