Metadata-Version: 2.1
Name: ops-py-generate-pyproject
Version: 2.2.3
Summary: Generate needed pyproject files to use with setuptools
License: MIT License
License-File: LICENSE
